testpackage_ammar/__init__.py
testpackage_ammar/__main__.py
testpackage_ammar/test_joke.py
testpackage_ammar/text.py
testpackage_ammar-1.0.dist-info/DESCRIPTION.rst
testpackage_ammar-1.0.dist-info/LICENSE.txt
testpackage_ammar-1.0.dist-info/METADATA
testpackage_ammar-1.0.dist-info/RECORD
testpackage_ammar-1.0.dist-info/WHEEL
testpackage_ammar-1.0.dist-info/entry_points.txt
testpackage_ammar-1.0.dist-info/metadata.json
testpackage_ammar-1.0.dist-info/top_level.txt
