Metadata-Version: 2.0
Name: testpackage-ammar
Version: 1.0
Summary: Some test methods
Home-page: http://github.com/atareen/testpackage
Author: Ammar Tareen
Author-email: tareen@cshl.edu
License: MIT
Keywords: Deployment testing JBK lab
Platform: UNKNOWN
Classifier: Development Status :: 3 - Alpha
Classifier: License :: OSI Approved :: MIT License
Classifier: Programming Language :: Python :: 2.7
Classifier: Topic :: Text Processing :: Linguistic
Requires-Dist: numpy
